AUTHORS
ChangeLog
README.md
setup.cfg
setup.py
murano.plugins.static_agent.egg-info/PKG-INFO
murano.plugins.static_agent.egg-info/SOURCES.txt
murano.plugins.static_agent.egg-info/dependency_links.txt
murano.plugins.static_agent.egg-info/entry_points.txt
murano.plugins.static_agent.egg-info/not-zip-safe
murano.plugins.static_agent.egg-info/pbr.json
murano.plugins.static_agent.egg-info/top_level.txt
static_agent/__init__.py