Metadata-Version: 1.0
Name: murano.plugins.static-agent
Version: 1.0.dev1
Summary: A plugin for Murano Engine which adds a custom MuranoPL class allowing to specify AMQP queue names statically instead of default random name generation
Home-page: UNKNOWN
Author: Alexander Tivelkov
Author-email: ativelkov@mirantis.com
License: UNKNOWN
Platform: UNKNOWN
